Jemish/main.py
jem_demoo-1.0.3.dist-info/LICENSE
jem_demoo-1.0.3.dist-info/METADATA
jem_demoo-1.0.3.dist-info/WHEEL
jem_demoo-1.0.3.dist-info/entry_points.txt
jem_demoo-1.0.3.dist-info/top_level.txt
jem_demoo-1.0.3.dist-info/RECORD
