Metadata-Version: 2.1
Name: jem-demoo
Version: 1.0.3
Summary: this pkg for compress the image
Home-page: UNKNOWN
Author: Jem's
Author-email: UNKNOWN
License: MIT
Platform: UNKNOWN
